keyengine/__init__.py
keyengine/console.py
keyengine/keydetection.py
keyengine/menus.py
keyengine-1.0.1.dist-info/METADATA
keyengine-1.0.1.dist-info/WHEEL
keyengine-1.0.1.dist-info/RECORD
