Metadata-Version: 2.3
Name: keyengine
Version: 1.0.1
Summary: A quick way to make interactive console interfaces that automatically listen to keyboard inputs.
Author: cornusandu
Author-email: cornusandu@hotmail.com
Requires-Python: >=3.11
Classifier: Programming Language :: Python :: 3
Classifier: Programming Language :: Python :: 3.11
Classifier: Programming Language :: Python :: 3.12
Classifier: Programming Language :: Python :: 3.13
Requires-Dist: colorama (>=0.4.6,<0.5.0)
Requires-Dist: keyboard (>=0.13.5,<0.14.0)
